how_now/__init__.py
how_now/foo.py
how_now-0.0.3.dist-info/LICENSE
how_now-0.0.3.dist-info/METADATA
how_now-0.0.3.dist-info/WHEEL
how_now-0.0.3.dist-info/RECORD
