Metadata-Version: 2.1
Name: how_now
Version: 0.0.3
Summary: Explain exceptions using AI.
Home-page: https://github.com/habemus-papadum/how-now
Author: Nehal Patel
Author-email: fnehal@alum.mit.edu
Requires-Python: >=3.8,<4.0
Classifier: Programming Language :: Python :: 3
Classifier: Programming Language :: Python :: 3.8
Classifier: Programming Language :: Python :: 3.9
Classifier: Programming Language :: Python :: 3.10
Classifier: Programming Language :: Python :: 3.11
Project-URL: Documentation, https://habemus-papadum.github.io/how-now/
Project-URL: Repository, https://github.com/habemus-papadum/how-now
